medidata/__init__.py
medidata/dataset.py
medidata/test.py
medidata-0.2.0.dist-info/METADATA
medidata-0.2.0.dist-info/WHEEL
medidata-0.2.0.dist-info/top_level.txt
medidata-0.2.0.dist-info/RECORD
